{
  "title": "麻雀 点数計算 覚え方 初心者の最短手順",
  "content": "# 麻雀 点数計算 覚え方 初心者の最短手順\n\n## この記事の結論\n- 麻雀 点数計算 覚え方 初心者の最短ルートは「満貫以下の頻出形を先に暗記し、符計算は後から足す」ことです。\n- 初心者は全パターンを覚えるより、出現頻度の高い30符・40符・満貫を優先すると実戦で困る回数が大きく減ります。\n- 点数計算は単なる暗記ではなく、リーチ判断・押し引き・オーラス条件に直結する戦術スキルです。\n\n## 基本理論\n\n### 点数計算は「期待値判断」の土台\n麻雀 点数計算 覚え方 初心者で最初に押さえるべきなのは、点数計算が和了（あがり）の後処理ではなく、局中の判断材料だという点です。\n\nたとえば同じリーチでも、子の1300点テンパイと満貫8000点テンパイでは押し引きが変わります。一般的な牌譜統計では、リーチの和了率はおおむね40%前後、放銃率は10%台前半とされます。つまり、打点が高いほど同じリスクを取る価値が上がります。\n\n初心者が最初に覚えるべき点数帯は次の通りです。\n\n| 子のロン | 30符 | 40符 | 50符 |\n|---|---:|---:|---:|\n| 1翻 | 1000 | 1300 | 1600 |\n| 2翻 | 2000 | 2600 | 3200 |\n| 3翻 | 3900 | 5200 | 6400 |\n| 4翻 | 7700 | 満貫 | 満貫 |\n\n| 親のロン | 30符 | 40符 | 50符 |\n|---|---:|---:|---:|\n| 1翻 | 1500 | 2000 | 2400 |\n| 2翻 | 2900 | 3900 | 4800 |\n| 3翻 | 5800 | 7700 | 9600 |\n| 4翻 | 11600 | 満貫 | 満貫 |\n\nこの表だけで、実戦のかなりの和了に対応できます。特に門前（鳴かずに進める手）リーチでは30符、鳴き手では30符・40符が頻出します。{{internal_link:符計算の基本}}\n\n### 初心者は「符」より「境界」を覚える\n点数計算で重要なのは、細かい符を全部覚えることではありません。初心者はまず、打点の境界を覚えるべきです。\n\n代表的な境界は次の3つです。\n\n- 子の3900と5200の差：押し返す価値が大きく変わる\n- 7700と満貫8000の差：実質ほぼ同じなので判断差は小さい\n- 8000と12000の差：順位条件に直結する\n\n特にオーラス（最終局）では、点数計算を間違えると「ツモ条件」「直撃条件」「満貫条件」を誤ります。麻雀 点数計算 覚え方 初心者の学習では、暗記表よりもまず順位が変わる点数を意識するのが効率的です。\n\n## 具体的な牌姿・場面例\n\n### 例1：リーチのみを嫌い、タンヤオ変化を見る\n牌姿：二三四(3)(4)(5)4567s東東白白\n\nドラ：なし 6巡目 子\n\n切る牌：白\n\nこの手は東と白の対子（同じ牌2枚）があり、どちらを残すか迷いやすい形です。白を切ると、東ポンで役牌（字牌の刻子で成立する役）3900未満の手になりやすい一方、索子の4567s部分に5s・8s受けが残ります。\n\n受入枚数だけを見ると、東・白のどちらかを切っても大差はありません。ただし東は場風や自風なら1翻が確定し、白は役牌として常に1翻です。ここでは白が1枚切れ、東が生牌なら東を残す価値が上がります。\n\n点数計算上の狙いは「リーチのみ1300」ではなく「役牌＋ドラや赤で3900以上」を作ることです。初心者は受入枚数だけでなく、最終打点をセットで見ると判断が安定します。\n\n### 例2：30符3翻と40符3翻の差を意識する\n牌姿：一二三(2)(3)(4)345s南南南中中\n\nドラ：中 8巡目 子\n\n切る牌：中を切らず、孤立牌があればそこから切る\n\nこの手は南が刻子（同じ牌3枚）、中が対子でドラです。中をポンできれば役牌ドラ3級の高打点になりやすく、ロンなら40符以上になりやすい形です。\n\n仮に南刻子＋中ドラ対子で和了すると、2翻止まりでも2600から3900、ドラが絡めば5200以上が見えます。30符3翻は3900、40符3翻は5200です。この1300点差は、平均順位に影響する大きな差です。\n\n受入枚数は両面（たとえば(2)(3)なら(1)(4)）が最大8枚、対子のポン材は最大2枚です。枚数では両面が有利ですが、点数上昇の幅を考えるとドラ対子を軽く扱ってはいけません。\n\n### 例3：満貫が見えるなら安全牌より打点維持\n牌姿：三四五(5)(6)(7)678s發發中中\n\nドラ：發 10巡目 親\n\n切る牌：中を基本的に残す\n\n發がドラ対子、中も役牌対子です。どちらかをポンできれば、親の満貫12000が現実的です。親の満貫は子の満貫8000より1.5倍高く、局収支への影響が非常に大きいです。\n\n受入枚数で見ると、面子は完成しており、發・中のポン材は各2枚、合計4枚です。リーチ手の両面8枚に比べると少なく見えますが、和了時の打点が高いので期待値は十分あります。\n\n初心者は「受入枚数が少ないから弱い」と判断しがちですが、麻雀は枚数×打点×安全度で評価します。麻雀 点数計算 覚え方 初心者の段階でも、この掛け算の感覚は早めに身につけたいところです。\n\n## 実戦での応用パターン\n\n### 東場 vs 南場での違い\n東場（前半戦）は、点数計算を「期待値最大化」に使います。3900が5200になるルート、5200が満貫になるルートを残すのが基本です。\n\n南場（後半戦）は、点数計算を「順位条件」に使います。たとえばトップと7000点差なら、子の満貫ツモでは2000・4000で逆転できる可能性があります。一方、3900ロンでは届かない場面もあります。\n\nつまり東場は打点効率、南場は必要点数が基準です。\n\n### 点数状況による判断の変化\n自分がトップなら、無理に満貫を狙わず、2000点や3900点で局を進める価値があります。逆にラス目なら、1000点の和了では順位が変わらないことが多く、リスクを取って満貫ルートを残す必要があります。\n\n特に初心者は「和了できそうだから鳴く」と考えがちです。しかし鳴いて1000点になるなら、門前でリーチ＋ツモ＋裏ドラのルートを残した方が局収支で勝ることがあります。{{internal_link:押し引き判断の基礎}}\n\n### 他家の捨て牌・副露状況からの読み\n他家が2副露（2回鳴いている状態）していて、役牌ポン＋ドラ色の切り出しが遅い場合、3900以上を想定します。点数計算ができると、相手の手を「安そう」「高そう」ではなく、1000・2000・3900・満貫のレンジで読めます。\n\nたとえば役牌ポン、ドラ1枚見え、赤ありルールなら、最低2000、赤やドラ重なりで3900以上が現実的です。こちらが1300点テンパイなら、終盤に無筋（危険牌）を押す価値は下がります。\n\n### 巡目による判断基準の変化\n序盤は打点上昇を重視します。6巡目までなら、受入枚数を少し落としてもドラ対子や役牌対子を残す価値があります。\n\n中盤の7〜12巡目は、受入枚数と打点のバランスです。両面8枚と愚形4枚なら、打点差が1翻以上あるかを基準にします。\n\n終盤の13巡目以降は、安全度が急に重要になります。満貫テンパイなら押せる場面もありますが、1000点や1300点では放銃率に見合わないことが増えます。\n\n## よくある間違い・罠\n\n### 罠1：符計算を完璧にしようとして挫折する\nこう打ちたくなる：全符パターンを最初から丸暗記する。\n\n実はこちらが正着：30符・40符・満貫を先に覚える。\n\n麻雀 点数計算 覚え方 初心者で最も多い失敗は、20符から110符まで一気に覚えようとすることです。実戦頻度を考えると、まず30符と40符で十分です。25符七対子（同じ牌2枚を7組作る役）は例外として、子1600・3200、親2400・4800を覚えれば対応できます。\n\n### 罠2：1000点和了を過大評価する\nこう打ちたくなる：鳴ける牌は全部鳴いて最速1000点にする。\n\n実はこちらが正着：順位が変わらない1000点なら、3900以上の変化を残す。\n\n和了率だけなら鳴きは強力です。副露によってテンパイ速度が上がる場面は多くあります。しかし、打点が1000点まで落ちると、放銃1回で簡単に帳消しになります。特に中盤以降、相手リーチに1000点で押すのは期待値が悪化しやすい判断です。\n\n### 罠3：満貫確定を見落とす\nこう打ちたくなる：符がわからないから安く申告してしまう。\n\n実はこちらが正着：3翻70符、4翻40符以上、5翻は満貫と覚える。\n\n点数申告で重要なのは、細かい符より満貫ラインです。5翻は符に関係なく満貫。4翻でも40符以上なら満貫。3翻でも70符以上なら満貫です。\n\nこの境界を覚えるだけで、申告ミスは大きく減ります。{{internal_link:満貫以上の点数早見表}}\n\n## まとめ：こんな場面で使おう\n\n麻雀 点数計算 覚え方 初心者の実戦チェックリストは次の通りです。\n\n- まず子の30符・40符、親の30符・40符を覚える\n- 7700と8000の差より、3900と5200の差を重視する\n- 東場は期待値、南場は順位条件で点数を見る\n- 鳴く前に「この手は1000点になるのか、3900以上が残るのか」を確認する\n- 終盤は打点が低いテンパイほど押し引きを厳しくする\n- 5翻は満貫、4翻40符以上も満貫と覚える\n- オーラスでは和了点ではなく、順位が変わる点数を逆算する\n\n点数計算は暗記科目に見えますが、実戦では押し引き、鳴き判断、リーチ判断、オーラス条件を支える分析ツールです。初心者はまず頻出点数を覚え、次に符計算を足していく順番が最短です。数値で判断できるようになると、感覚だけの麻雀から一段抜け出せます。",
  "meta_description": "麻雀初心者向けに点数計算の覚え方を解説。30符・40符・満貫を軸に、実戦判断へつなげます。",
  "tags": [
    "麻雀",
    "点数計算",
    "符計算",
    "初心者",
    "麻雀戦術"
  ],
  "slug": "mahjong-score-beginner-guide",
  "hero_emoji": "📝",
  "hero_gradient": "135deg",
  "image_search_query": "",
  "keyword": "麻雀 点数計算 覚え方 初心者",
  "category": "点数計算・符計算",
  "generated_at": "2026-05-20T09:03:11.704383"
}